mlb_realtime-0.0.11.dist-info/entry_points.txt
mlb_realtime-0.0.11.dist-info/top_level.txt
mlb_realtime-0.0.11.dist-info/METADATA
mlb_realtime-0.0.11.dist-info/RECORD
mlb_realtime-0.0.11.dist-info/WHEEL
mlb_realtime-0.0.11.dist-info/DESCRIPTION.rst
mlb_realtime-0.0.11.dist-info/metadata.json
command_line/__init__.py
command_line/client.py
realtime/time_converter.py
realtime/parse.py
realtime/url_builder.py
realtime/link_finder.py
realtime/__init__.py
realtime/__main__.py
realtime/database.py
realtime/client.py
realtime/test.py
