Metadata-Version: 2.0
Name: mlb-realtime
Version: 0.0.11
Summary: Real time baseball updates
Home-page: https://github.com/ecowan/mlb-realtime/
Author: Ethan Cowan
Author-email: ethan24@gmail.com
License: MIT
Keywords: baseball
Platform: UNKNOWN
Classifier: Development Status :: 3 - Alpha
Classifier: Intended Audience :: Developers
Classifier: Topic :: Software Development :: Build Tools
Classifier: License :: OSI Approved :: MIT License
Classifier: Programming Language :: Python :: 2
Classifier: Programming Language :: Python :: 2.6
Classifier: Programming Language :: Python :: 2.7
Requires-Dist: pytz
Requires-Dist: requests
Requires-Dist: beautifulsoup4
Provides-Extra: test
Requires-Dist: coverage; extra == 'test'
Provides-Extra: dev
Requires-Dist: check-manifest; extra == 'dev'
